odoo9_addon_web_sheet_full_width-9.0.1.0.0.99.dev3-py2.7-nspkg.pth
odoo_addons/web_sheet_full_width/__openerp__.py
odoo_addons/web_sheet_full_width/__init__.py
odoo_addons/web_sheet_full_width/README.rst
odoo_addons/web_sheet_full_width/view/qweb.xml
odoo_addons/web_sheet_full_width/static/description/icon.png
odoo_addons/web_sheet_full_width/static/src/css/web_sheet_full_width.css
odoo9_addon_web_sheet_full_width-9.0.1.0.0.99.dev3.dist-info/top_level.txt
odoo9_addon_web_sheet_full_width-9.0.1.0.0.99.dev3.dist-info/WHEEL
odoo9_addon_web_sheet_full_width-9.0.1.0.0.99.dev3.dist-info/RECORD
odoo9_addon_web_sheet_full_width-9.0.1.0.0.99.dev3.dist-info/metadata.json
odoo9_addon_web_sheet_full_width-9.0.1.0.0.99.dev3.dist-info/DESCRIPTION.rst
odoo9_addon_web_sheet_full_width-9.0.1.0.0.99.dev3.dist-info/METADATA
odoo9_addon_web_sheet_full_width-9.0.1.0.0.99.dev3.dist-info/namespace_packages.txt
