Metadata-Version: 2.0
Name: odoo9-addon-web-sheet-full-width
Version: 9.0.1.0.0.99.dev3
Summary: Use the whole available screen width when displaying sheets
Home-page: UNKNOWN
Author: UNKNOWN
Author-email: UNKNOWN
License: AGPL-3
Platform: UNKNOWN
Requires-Dist: odoo (<9.1a,>=9.0a)
Classifier: Programming Language :: Python :: 2.7
Classifier: Framework :: Odoo
Classifier: License :: OSI Approved :: GNU Affero General Public License v3
